CHANGES.txt
MANIFEST.in
README.txt
setup.py
isotoma/__init__.py
isotoma.recipe.django.egg-info/PKG-INFO
isotoma.recipe.django.egg-info/SOURCES.txt
isotoma.recipe.django.egg-info/dependency_links.txt
isotoma.recipe.django.egg-info/entry_points.txt
isotoma.recipe.django.egg-info/not-zip-safe
isotoma.recipe.django.egg-info/requires.txt
isotoma.recipe.django.egg-info/top_level.txt
isotoma/recipe/__init__.py
isotoma/recipe/django/__init__.py
isotoma/recipe/django/recipe.py
isotoma/recipe/django/wsgi.py
isotoma/recipe/django/templates/production.tmpl
isotoma/recipe/django/templates/settings.tmpl
isotoma/recipe/django/templates/setup.tmpl
isotoma/recipe/django/templates/staging.tmpl
isotoma/recipe/django/templates/urls.tmpl
isotoma/recipe/django/templates/wsgi.tmpl