Metadata-Version: 1.0
Name: isotoma.recipe.django
Version: 3.1.2
Summary: Buildout recipe for Django
Home-page: http://github.com/isotoma
Author: Tom Wardill
Author-email: tom.wardill@isotoma.com
License: BSD
Platform: UNKNOWN
Classifier: Framework :: Buildout
Classifier: Framework :: Django
Classifier: Topic :: Software Development :: Build Tools
Classifier: Development Status :: 5 - Production/Stable
Classifier: License :: OSI Approved :: BSD License
